{
  "_class": "group",
  "do_objectID": "0BA3F197-16B0-4A16-80A2-7B93C94CA6AF",
  "exportOptions": {
    "_class": "exportOptions",
    "do_objectID": "35B938F8-8BC4-42C0-9C36-6F359B416DB5",
    "exportFormats": [
    ],
    "includedLayerIds": [
    ],
    "layerOptions": 0,
    "shouldTrim": false
  },
  "frame": {
    "_class": "rect",
    "constrainProportions": false,
    "do_objectID": "C3A8DD66-A992-48E5-BF77-887D2FADCB17",
    "height": 28,
    "width": 355,
    "x": 890,
    "y": 863
  },
  "hasClickThrough": false,
  "isFlippedHorizontal": false,
  "isFlippedVertical": false,
  "isLocked": false,
  "isVisible": true,
  "layerListExpandedType": 0,
  "layers": [
    {
      "class": "text",
      "id": "4674E854-229A-4DDD-80B9-E4BFBB4C90FD"
    },
    {
      "class": "text",
      "id": "850796AE-89CF-433E-B475-4E58083844EE"
    }
  ],
  "name": "Group 5142",
  "nameIsFixed": false,
  "resizingConstraint": 63,
  "resizingType": 0,
  "rotation": 0,
  "shouldBreakMaskChain": false,
  "style": {
    "_class": "style",
    "do_objectID": "34157755-32B7-4DCE-B2BA-BD26D3A67DF4",
    "endDecorationType": 0,
    "miterLimit": 10,
    "startDecorationType": 0
  }
}