{
  "_class": "shapeGroup",
  "clippingMaskMode": 0,
  "do_objectID": "B1BC60B2-C0BE-4E43-9C18-8CA2267E198E",
  "exportOptions": {
    "_class": "exportOptions",
    "do_objectID": "8262A44A-3701-4367-B976-73810CACAD3F",
    "exportFormats": [
    ],
    "includedLayerIds": [
    ],
    "layerOptions": 0,
    "shouldTrim": false
  },
  "frame": {
    "_class": "rect",
    "constrainProportions": false,
    "do_objectID": "79F04806-5913-4CD0-95D6-501B9C86F593",
    "height": 83.94999999999999,
    "width": 83.94999999999999,
    "x": 13.8,
    "y": 3.45
  },
  "hasClickThrough": false,
  "hasClippingMask": true,
  "isFlippedHorizontal": false,
  "isFlippedVertical": false,
  "isLocked": false,
  "isVisible": true,
  "layerListExpandedType": 2,
  "layers": [
    {
      "class": "shapePath",
      "id": "BA880CEC-26D2-4867-AA63-5E343EBB8AC1"
    }
  ],
  "name": "Empty",
  "nameIsFixed": false,
  "resizingConstraint": 63,
  "resizingType": 0,
  "rotation": 0,
  "shouldBreakMaskChain": false,
  "style": {
    "_class": "style",
    "blur": {
      "_class": "blur",
      "center": "{0.5, 0.5}",
      "do_objectID": "0FCC877B-8D49-483C-942E-C926CEF9A5EC",
      "isEnabled": false,
      "motionAngle": 0,
      "radius": 11.5,
      "type": 0
    },
    "borders": [
      {
        "_class": "border",
        "color": {
          "_class": "color",
          "alpha": 1,
          "blue": 0.9647059,
          "green": 0.9411765,
          "red": 0.9254902
        },
        "fillType": 0,
        "isEnabled": true,
        "position": 1,
        "thickness": 6.899999999999999
      }
    ],
    "do_objectID": "E6847669-132A-4337-9771-B5B8D5BE56E4",
    "endDecorationType": 0,
    "fills": [
      {
        "_class": "fill",
        "color": {
          "_class": "color",
          "alpha": 0,
          "blue": 0,
          "green": 0,
          "red": 0
        },
        "fillType": 0,
        "isEnabled": true,
        "noiseIndex": 0,
        "noiseIntensity": 0,
        "patternFillType": 1,
        "patternTileScale": 1
      }
    ],
    "miterLimit": 10,
    "startDecorationType": 0
  },
  "windingRule": 1
}