{
  "_class": "group",
  "do_objectID": "BC1C6910-B470-4E20-8E85-0198BD4EDCCB",
  "exportOptions": {
    "_class": "exportOptions",
    "do_objectID": "6B79713F-40C9-4289-86F7-47313D36E56D",
    "exportFormats": [
    ],
    "includedLayerIds": [
    ],
    "layerOptions": 0,
    "shouldTrim": false
  },
  "frame": {
    "_class": "rect",
    "constrainProportions": false,
    "do_objectID": "213EE7FA-E8A3-4D4B-BB63-F5F55E961365",
    "height": 87,
    "width": 147,
    "x": 201,
    "y": 1540
  },
  "hasClickThrough": false,
  "isFlippedHorizontal": false,
  "isFlippedVertical": false,
  "isLocked": false,
  "isVisible": false,
  "layerListExpandedType": 0,
  "layers": [
    {
      "class": "group",
      "id": "B4A3219C-F985-41CD-9300-FABA41C403A7"
    },
    {
      "class": "shapeGroup",
      "id": "79178CC0-91BE-49DD-AFF4-A68CE7841FB9"
    },
    {
      "class": "group",
      "id": "773B5E31-9DAA-419D-999A-3682FBC719D1"
    },
    {
      "class": "shapeGroup",
      "id": "D0426710-04D7-4E35-A894-1DAB6188DAD9"
    },
    {
      "class": "shapeGroup",
      "id": "06F3D0BF-5FFF-438D-A30C-5F2A7768B945"
    }
  ],
  "name": "cronica-zapatilla",
  "nameIsFixed": true,
  "resizingConstraint": 63,
  "resizingType": 0,
  "rotation": 0,
  "shouldBreakMaskChain": false,
  "style": {
    "_class": "style",
    "do_objectID": "0CA4DF05-8136-4565-8D3D-8716B87AC57F",
    "endDecorationType": 0,
    "miterLimit": 10,
    "startDecorationType": 0
  }
}