{
  "_class": "bitmap",
  "clippingMask": "{{0, 0}, {1, 1}}",
  "do_objectID": "262120F2-D0DA-4958-ADCD-165436DC1DE5",
  "exportOptions": {
    "_class": "exportOptions",
    "do_objectID": "A645EAA6-21C7-486B-8F96-2A2FD8916031",
    "exportFormats": [
    ],
    "includedLayerIds": [
    ],
    "layerOptions": 0,
    "shouldTrim": false
  },
  "fillReplacesImage": false,
  "frame": {
    "_class": "rect",
    "constrainProportions": true,
    "do_objectID": "80436757-773B-4221-9ABA-C64F8DB9FF71",
    "height": 510,
    "width": 510,
    "x": 0,
    "y": 0
  },
  "image": {
    "_class": "MSJSONFileReference",
    "_ref": "images/0bd490937d6347a76eba7151e11b31e101f38ce1",
    "_ref_class": "MSImageData"
  },
  "isFlippedHorizontal": false,
  "isFlippedVertical": false,
  "isLocked": false,
  "isVisible": true,
  "layerListExpandedType": 0,
  "name": "Bitmap",
  "nameIsFixed": false,
  "resizingConstraint": 63,
  "resizingType": 0,
  "rotation": 0,
  "shouldBreakMaskChain": false,
  "style": {
    "_class": "style",
    "do_objectID": "56CD4710-6840-47F0-B19D-A20E8F198F49",
    "endDecorationType": 0,
    "miterLimit": 10,
    "startDecorationType": 0
  }
}