{
  "_class": "bitmap",
  "clippingMask": "{{0, 0}, {1, 1}}",
  "do_objectID": "7D4DB890-C147-47C7-9E99-BEE8DB3B2C95",
  "exportOptions": {
    "_class": "exportOptions",
    "do_objectID": "B94572AC-6784-489E-B4FD-BFF9D5A644EE",
    "exportFormats": [
    ],
    "includedLayerIds": [
    ],
    "layerOptions": 0,
    "shouldTrim": false
  },
  "fillReplacesImage": false,
  "frame": {
    "_class": "rect",
    "constrainProportions": false,
    "do_objectID": "28B112DD-1814-41C2-9D61-0AD066503BAA",
    "height": 27.6,
    "width": 23,
    "x": 28.75,
    "y": 51.75
  },
  "image": {
    "_class": "MSJSONFileReference",
    "_ref": "images/61c0e502139b383d720be9870caa0b6b56a0ec73",
    "_ref_class": "MSImageData"
  },
  "isFlippedHorizontal": false,
  "isFlippedVertical": false,
  "isLocked": false,
  "isVisible": true,
  "layerListExpandedType": 1,
  "name": "TEAM LOGO",
  "nameIsFixed": false,
  "resizingConstraint": 63,
  "resizingType": 0,
  "rotation": 0,
  "shouldBreakMaskChain": false,
  "style": {
    "_class": "style",
    "blur": {
      "_class": "blur",
      "center": "{0.5, 0.5}",
      "do_objectID": "2C795D5F-6F8D-4CED-B88A-6E6D0B5D644B",
      "isEnabled": false,
      "motionAngle": 0,
      "radius": 11.5,
      "type": 0
    },
    "do_objectID": "B8C65EF6-432E-427F-BD5F-2440B7FC046A",
    "endDecorationType": 0,
    "fills": [
      {
        "_class": "fill",
        "color": {
          "_class": "color",
          "alpha": 0,
          "blue": 0,
          "green": 0,
          "red": 0
        },
        "fillType": 0,
        "isEnabled": true,
        "noiseIndex": 0,
        "noiseIntensity": 0,
        "patternFillType": 1,
        "patternTileScale": 1
      }
    ],
    "miterLimit": 10,
    "startDecorationType": 0
  }
}