{
  "_class": "group",
  "do_objectID": "8E4BFDEF-08EB-4438-99AE-DB899C3BF39B",
  "exportOptions": {
    "_class": "exportOptions",
    "do_objectID": "20CB8B94-DB51-469D-9DDA-1445448B8DB0",
    "exportFormats": [
    ],
    "includedLayerIds": [
    ],
    "layerOptions": 0,
    "shouldTrim": false
  },
  "frame": {
    "_class": "rect",
    "constrainProportions": false,
    "do_objectID": "5FD86BA3-9CF3-4682-9EED-2B3F290E1CCD",
    "height": 45,
    "width": 120,
    "x": 11,
    "y": 11
  },
  "hasClickThrough": false,
  "isFlippedHorizontal": false,
  "isFlippedVertical": false,
  "isLocked": false,
  "isVisible": true,
  "layerListExpandedType": 0,
  "layers": [
    {
      "class": "shapeGroup",
      "id": "5AE3697F-AD65-400F-9AF0-11261B5E2898"
    },
    {
      "class": "shapeGroup",
      "id": "C15CAB77-33BB-46E4-ABFC-CAB14E9FBECE"
    }
  ],
  "name": "Group 47",
  "nameIsFixed": false,
  "resizingConstraint": 63,
  "resizingType": 0,
  "rotation": 0,
  "shouldBreakMaskChain": false,
  "style": {
    "_class": "style",
    "do_objectID": "37F10936-6933-4727-B53B-450115D55C44",
    "endDecorationType": 0,
    "miterLimit": 10,
    "startDecorationType": 0
  }
}