{
  "_class": "shapePath",
  "booleanOperation": -1,
  "do_objectID": "6427A22E-5025-4758-9850-C39D9BFE305B",
  "edited": true,
  "exportOptions": {
    "_class": "exportOptions",
    "do_objectID": "65652A5E-ABD7-49FA-AF40-3758D83DAF4D",
    "exportFormats": [
    ],
    "includedLayerIds": [
    ],
    "layerOptions": 0,
    "shouldTrim": false
  },
  "frame": {
    "_class": "rect",
    "constrainProportions": false,
    "do_objectID": "89353D1A-7933-4D5E-944E-A889DB1D3608",
    "height": 8.51546391752574,
    "width": 2.449999999999996,
    "x": 19.59999999999997,
    "y": 18.24742268041236
  },
  "isClosed": true,
  "isFlippedHorizontal": false,
  "isFlippedVertical": false,
  "isLocked": false,
  "isVisible": true,
  "layerListExpandedType": 0,
  "name": "Path",
  "nameIsFixed": false,
  "path": {
    "_class": "path",
    "isClosed": true,
    "pointRadiusBehaviour": 1,
    "points": [
      {
        "_class": "curvePoint",
        "cornerRadius": 0,
        "curveFrom": "{0.080291127541588805, 0}",
        "curveMode": 1,
        "curveTo": "{0.080291127541588805, 0}",
        "hasCurveFrom": false,
        "hasCurveTo": false,
        "point": "{0.080291127541588805, 0}"
      },
      {
        "_class": "curvePoint",
        "cornerRadius": 0,
        "curveFrom": "{0, 0.012166083785995908}",
        "curveMode": 1,
        "curveTo": "{0, 0.012166083785995908}",
        "hasCurveFrom": false,
        "hasCurveTo": false,
        "point": "{0, 0.012166083785995908}"
      },
      {
        "_class": "curvePoint",
        "cornerRadius": 0,
        "curveFrom": "{0.22262014787430581, 0.060756008631594943}",
        "curveMode": 1,
        "curveTo": "{0.22262014787430581, 0.060756008631594943}",
        "hasCurveFrom": false,
        "hasCurveTo": false,
        "point": "{0.22262014787430581, 0.060756008631594943}"
      },
      {
        "_class": "curvePoint",
        "cornerRadius": 0,
        "curveFrom": "{0.91670517560073905, 1}",
        "curveMode": 1,
        "curveTo": "{0.91670517560073905, 1}",
        "hasCurveFrom": false,
        "hasCurveTo": false,
        "point": "{0.91670517560073905, 1}"
      },
      {
        "_class": "curvePoint",
        "cornerRadius": 0,
        "curveFrom": "{1, 0.98712701837934358}",
        "curveMode": 1,
        "curveTo": "{1, 0.98712701837934358}",
        "hasCurveFrom": false,
        "hasCurveTo": false,
        "point": "{1, 0.98712701837934358}"
      },
      {
        "_class": "curvePoint",
        "cornerRadius": 0,
        "curveFrom": "{0.30210258780037053, 0.047957437309324169}",
        "curveMode": 1,
        "curveTo": "{0.30210258780037053, 0.047957437309324169}",
        "hasCurveFrom": false,
        "hasCurveTo": false,
        "point": "{0.30210258780037053, 0.047957437309324169}"
      }
    ]
  },
  "pointRadiusBehaviour": 1,
  "points": [
    {
      "_class": "curvePoint",
      "cornerRadius": 0,
      "curveFrom": "{0.080291127541588805, 0}",
      "curveMode": 1,
      "curveTo": "{0.080291127541588805, 0}",
      "hasCurveFrom": false,
      "hasCurveTo": false,
      "point": "{0.080291127541588805, 0}"
    },
    {
      "_class": "curvePoint",
      "cornerRadius": 0,
      "curveFrom": "{0, 0.012166083785995908}",
      "curveMode": 1,
      "curveTo": "{0, 0.012166083785995908}",
      "hasCurveFrom": false,
      "hasCurveTo": false,
      "point": "{0, 0.012166083785995908}"
    },
    {
      "_class": "curvePoint",
      "cornerRadius": 0,
      "curveFrom": "{0.22262014787430581, 0.060756008631594943}",
      "curveMode": 1,
      "curveTo": "{0.22262014787430581, 0.060756008631594943}",
      "hasCurveFrom": false,
      "hasCurveTo": false,
      "point": "{0.22262014787430581, 0.060756008631594943}"
    },
    {
      "_class": "curvePoint",
      "cornerRadius": 0,
      "curveFrom": "{0.91670517560073905, 1}",
      "curveMode": 1,
      "curveTo": "{0.91670517560073905, 1}",
      "hasCurveFrom": false,
      "hasCurveTo": false,
      "point": "{0.91670517560073905, 1}"
    },
    {
      "_class": "curvePoint",
      "cornerRadius": 0,
      "curveFrom": "{1, 0.98712701837934358}",
      "curveMode": 1,
      "curveTo": "{1, 0.98712701837934358}",
      "hasCurveFrom": false,
      "hasCurveTo": false,
      "point": "{1, 0.98712701837934358}"
    },
    {
      "_class": "curvePoint",
      "cornerRadius": 0,
      "curveFrom": "{0.30210258780037053, 0.047957437309324169}",
      "curveMode": 1,
      "curveTo": "{0.30210258780037053, 0.047957437309324169}",
      "hasCurveFrom": false,
      "hasCurveTo": false,
      "point": "{0.30210258780037053, 0.047957437309324169}"
    }
  ],
  "resizingConstraint": 63,
  "resizingType": 0,
  "rotation": 0,
  "shouldBreakMaskChain": false
}