{
  "_class": "bitmap",
  "clippingMask": "{{0, 0}, {1, 1}}",
  "do_objectID": "A9C89C6A-EC50-482F-9661-4B9EE0F5034D",
  "exportOptions": {
    "_class": "exportOptions",
    "do_objectID": "E293CA30-EA9B-4DD0-821B-E2D90B831D59",
    "exportFormats": [
    ],
    "includedLayerIds": [
    ],
    "layerOptions": 0,
    "shouldTrim": false
  },
  "fillReplacesImage": false,
  "frame": {
    "_class": "rect",
    "constrainProportions": false,
    "do_objectID": "781E0A97-D1DE-4570-B2B4-CC002FB24EB7",
    "height": 89,
    "width": 72,
    "x": -1,
    "y": -8
  },
  "image": {
    "_class": "MSJSONFileReference",
    "_ref": "images/9003c7c359891da6a2166f8aac6a47b687e3f7b1",
    "_ref_class": "MSImageData"
  },
  "isFlippedHorizontal": false,
  "isFlippedVertical": false,
  "isLocked": false,
  "isVisible": true,
  "layerListExpandedType": 0,
  "name": "Image 4883",
  "nameIsFixed": false,
  "resizingConstraint": 63,
  "resizingType": 0,
  "rotation": 0,
  "shouldBreakMaskChain": false,
  "style": {
    "_class": "style",
    "do_objectID": "2B803EF2-7820-4DCC-AD6A-991280127C02",
    "endDecorationType": 0,
    "miterLimit": 10,
    "startDecorationType": 0
  }
}