{
  "_class": "shapePath",
  "booleanOperation": 0,
  "do_objectID": "C2E6457B-74C8-48D9-A91F-D5C11B3F6DFB",
  "edited": false,
  "exportOptions": {
    "_class": "exportOptions",
    "do_objectID": "687CC22C-484C-418A-A919-3F3568B13939",
    "exportFormats": [
    ],
    "includedLayerIds": [
    ],
    "layerOptions": 0,
    "shouldTrim": false
  },
  "frame": {
    "_class": "rect",
    "constrainProportions": false,
    "do_objectID": "CD0D1CC9-6F15-4C9C-9252-927011AFAED6",
    "height": 13.60611854684502,
    "width": 12.4614045658432,
    "x": -2.15448961960262,
    "y": -1.629795304015329
  },
  "isClosed": true,
  "isFlippedHorizontal": false,
  "isFlippedVertical": false,
  "isLocked": false,
  "isVisible": true,
  "layerListExpandedType": 0,
  "name": "Shape sp-48327-0",
  "nameIsFixed": false,
  "path": {
    "_class": "path",
    "isClosed": true,
    "pointRadiusBehaviour": 0,
    "points": [
      {
        "_class": "curvePoint",
        "cornerRadius": 0,
        "curveFrom": "{0.17289299999999999, 0.28645199999999998}",
        "curveMode": 1,
        "curveTo": "{0.17289299999999999, 0.28645199999999998}",
        "hasCurveFrom": false,
        "hasCurveTo": false,
        "point": "{0.17289299999999999, 0.28645199999999998}"
      },
      {
        "_class": "curvePoint",
        "cornerRadius": 0,
        "curveFrom": "{0.48780800000000002, 0.119784}",
        "curveMode": 1,
        "curveTo": "{0.48780800000000002, 0.119784}",
        "hasCurveFrom": false,
        "hasCurveTo": false,
        "point": "{0.48780800000000002, 0.119784}"
      },
      {
        "_class": "curvePoint",
        "cornerRadius": 0,
        "curveFrom": "{0.85144299999999995, 0.69713000000000003}",
        "curveMode": 1,
        "curveTo": "{0.85144299999999995, 0.69713000000000003}",
        "hasCurveFrom": false,
        "hasCurveTo": false,
        "point": "{0.85144299999999995, 0.69713000000000003}"
      },
      {
        "_class": "curvePoint",
        "cornerRadius": 0,
        "curveFrom": "{0.53652699999999998, 0.863815}",
        "curveMode": 1,
        "curveTo": "{0.53652699999999998, 0.863815}",
        "hasCurveFrom": false,
        "hasCurveTo": false,
        "point": "{0.53652699999999998, 0.863815}"
      }
    ]
  },
  "pointRadiusBehaviour": 0,
  "points": [
    {
      "_class": "curvePoint",
      "cornerRadius": 0,
      "curveFrom": "{0.17289299999999999, 0.28645199999999998}",
      "curveMode": 1,
      "curveTo": "{0.17289299999999999, 0.28645199999999998}",
      "hasCurveFrom": false,
      "hasCurveTo": false,
      "point": "{0.17289299999999999, 0.28645199999999998}"
    },
    {
      "_class": "curvePoint",
      "cornerRadius": 0,
      "curveFrom": "{0.48780800000000002, 0.119784}",
      "curveMode": 1,
      "curveTo": "{0.48780800000000002, 0.119784}",
      "hasCurveFrom": false,
      "hasCurveTo": false,
      "point": "{0.48780800000000002, 0.119784}"
    },
    {
      "_class": "curvePoint",
      "cornerRadius": 0,
      "curveFrom": "{0.85144299999999995, 0.69713000000000003}",
      "curveMode": 1,
      "curveTo": "{0.85144299999999995, 0.69713000000000003}",
      "hasCurveFrom": false,
      "hasCurveTo": false,
      "point": "{0.85144299999999995, 0.69713000000000003}"
    },
    {
      "_class": "curvePoint",
      "cornerRadius": 0,
      "curveFrom": "{0.53652699999999998, 0.863815}",
      "curveMode": 1,
      "curveTo": "{0.53652699999999998, 0.863815}",
      "hasCurveFrom": false,
      "hasCurveTo": false,
      "point": "{0.53652699999999998, 0.863815}"
    }
  ],
  "resizingConstraint": 63,
  "resizingType": 0,
  "rotation": 0,
  "shouldBreakMaskChain": false
}