{
  "_class": "group",
  "do_objectID": "2BB7C001-B404-4F11-895B-05CB2C20CD67",
  "exportOptions": {
    "_class": "exportOptions",
    "do_objectID": "E88A1CB7-2080-47DB-8AF1-2D472200F152",
    "exportFormats": [
    ],
    "includedLayerIds": [
    ],
    "layerOptions": 0,
    "shouldTrim": false
  },
  "frame": {
    "_class": "rect",
    "constrainProportions": false,
    "do_objectID": "DDEAFE26-7292-4F9D-B539-646ED54BA0CF",
    "height": 68,
    "width": 1292,
    "x": 0,
    "y": 0
  },
  "hasClickThrough": false,
  "isFlippedHorizontal": false,
  "isFlippedVertical": false,
  "isLocked": false,
  "isVisible": true,
  "layerListExpandedType": 0,
  "layers": [
    {
      "class": "group",
      "id": "14B3E5C6-7A0F-4531-AB77-365C14581D83"
    },
    {
      "class": "group",
      "id": "D2FC3817-9C5F-476F-B293-585355FCCE0B"
    }
  ],
  "name": "Group 2989",
  "nameIsFixed": false,
  "resizingConstraint": 63,
  "resizingType": 0,
  "rotation": 0,
  "shouldBreakMaskChain": false,
  "style": {
    "_class": "style",
    "do_objectID": "052C01C7-1307-4E8F-806C-2A17C7BB3373",
    "endDecorationType": 0,
    "miterLimit": 10,
    "startDecorationType": 0
  }
}