{
  "_class": "group",
  "do_objectID": "1958300C-2CCE-42C7-B26B-BCE24C9DB3B5",
  "exportOptions": {
    "_class": "exportOptions",
    "do_objectID": "79DBDEB5-030D-490B-93E7-28D36E648949",
    "exportFormats": [
    ],
    "includedLayerIds": [
    ],
    "layerOptions": 0,
    "shouldTrim": false
  },
  "frame": {
    "_class": "rect",
    "constrainProportions": false,
    "do_objectID": "77DBEB9B-D45D-4753-9030-6A8C2AEFDC73",
    "height": 2,
    "width": 1344,
    "x": 49,
    "y": 872
  },
  "hasClickThrough": false,
  "isFlippedHorizontal": false,
  "isFlippedVertical": false,
  "isLocked": false,
  "isVisible": true,
  "layerListExpandedType": 0,
  "layers": [
    {
      "class": "shapeGroup",
      "id": "018E06FB-E196-4A0A-8F73-F9A654C1E9AB"
    },
    {
      "class": "shapeGroup",
      "id": "0B6DE758-174E-4321-BF34-D144219357AE"
    }
  ],
  "name": "Group 110",
  "nameIsFixed": false,
  "resizingConstraint": 63,
  "resizingType": 0,
  "rotation": 0,
  "shouldBreakMaskChain": false,
  "style": {
    "_class": "style",
    "do_objectID": "F653422C-F096-4A69-B11D-F15B46D9675D",
    "endDecorationType": 0,
    "miterLimit": 10,
    "startDecorationType": 0
  }
}