{
  "_class": "group",
  "do_objectID": "AA4EB27C-B07E-48AD-9769-4AEC8C96D36F",
  "exportOptions": {
    "_class": "exportOptions",
    "do_objectID": "25498737-0C03-49E1-B4EC-67CF6B9D6ACE",
    "exportFormats": [
    ],
    "includedLayerIds": [
    ],
    "layerOptions": 0,
    "shouldTrim": false
  },
  "frame": {
    "_class": "rect",
    "constrainProportions": false,
    "do_objectID": "49002B35-3023-4498-A767-E794DBBBB85B",
    "height": 324,
    "width": 390,
    "x": 873,
    "y": 853
  },
  "hasClickThrough": false,
  "isFlippedHorizontal": false,
  "isFlippedVertical": false,
  "isLocked": false,
  "isVisible": true,
  "layerListExpandedType": 0,
  "layers": [
    {
      "class": "shapeGroup",
      "id": "3C2C4A93-3B38-478A-948E-9D82DC41DA07"
    },
    {
      "class": "shapeGroup",
      "id": "B1F0FF89-E559-4D7E-AF79-51DF1643812E"
    }
  ],
  "name": "Group 5131",
  "nameIsFixed": false,
  "resizingConstraint": 63,
  "resizingType": 0,
  "rotation": 0,
  "shouldBreakMaskChain": false,
  "style": {
    "_class": "style",
    "do_objectID": "EF68B1F1-E02C-403A-A370-16178138CA91",
    "endDecorationType": 0,
    "miterLimit": 10,
    "startDecorationType": 0
  }
}