{
  "_class": "shapeGroup",
  "clippingMaskMode": 0,
  "do_objectID": "CA8A303C-8EE8-4597-9607-FBD86026A30B",
  "exportOptions": {
    "_class": "exportOptions",
    "do_objectID": "55F26F6E-5676-47DC-86A1-BA67985CA974",
    "exportFormats": [
    ],
    "includedLayerIds": [
    ],
    "layerOptions": 0,
    "shouldTrim": false
  },
  "frame": {
    "_class": "rect",
    "constrainProportions": false,
    "do_objectID": "0D296E54-FD41-4181-B39B-9A8701C51FCB",
    "height": 3.330593249636085,
    "width": 4.000224757933648,
    "x": 8.492470027822876,
    "y": 9.835395890567026
  },
  "hasClickThrough": false,
  "hasClippingMask": false,
  "isFlippedHorizontal": false,
  "isFlippedVertical": false,
  "isLocked": false,
  "isVisible": true,
  "layerListExpandedType": 2,
  "layers": [
    {
      "class": "shapePath",
      "id": "7E1F53F4-FBD9-4C42-B2F6-245BACE42AD9"
    }
  ],
  "name": "Black Detail",
  "nameIsFixed": false,
  "resizingConstraint": 63,
  "resizingType": 0,
  "rotation": 0,
  "shouldBreakMaskChain": false,
  "style": {
    "_class": "style",
    "do_objectID": "A421CA7C-4C38-468B-9B77-19856829D5B3",
    "endDecorationType": 0,
    "fills": [
      {
        "_class": "fill",
        "color": {
          "_class": "color",
          "alpha": 1,
          "blue": 0.29411766,
          "green": 0.28235295,
          "red": 0.2509804
        },
        "fillType": 0,
        "isEnabled": true,
        "noiseIndex": 0,
        "noiseIntensity": 0,
        "patternFillType": 1,
        "patternTileScale": 1
      }
    ],
    "miterLimit": 10,
    "startDecorationType": 0
  },
  "windingRule": 1
}