{
  "_class": "group",
  "do_objectID": "2F0692CA-55A8-4B64-BAC6-A3DBB2D0DE87",
  "exportOptions": {
    "_class": "exportOptions",
    "do_objectID": "2A3CDD4B-A988-4A2E-8A78-B14268FD0719",
    "exportFormats": [
    ],
    "includedLayerIds": [
    ],
    "layerOptions": 0,
    "shouldTrim": false
  },
  "frame": {
    "_class": "rect",
    "constrainProportions": false,
    "do_objectID": "2880305A-9238-42F0-B853-7282F7B1092A",
    "height": 271,
    "width": 355,
    "x": 108,
    "y": 894
  },
  "hasClickThrough": false,
  "isFlippedHorizontal": false,
  "isFlippedVertical": false,
  "isLocked": false,
  "isVisible": true,
  "layerListExpandedType": 0,
  "layers": [
    {
      "class": "text",
      "id": "66A8065C-E047-45D8-97A3-E318C7DEBCEB"
    },
    {
      "class": "text",
      "id": "F3DBB306-EB16-4CB0-AEAE-EEBA592DB4AC"
    },
    {
      "class": "text",
      "id": "4A2371AF-51E5-4722-9DCD-9C6203BD5587"
    },
    {
      "class": "text",
      "id": "C801A595-DAD4-4D0B-90B1-0F0C437BB424"
    }
  ],
  "name": "Group 3629",
  "nameIsFixed": false,
  "resizingConstraint": 63,
  "resizingType": 0,
  "rotation": 0,
  "shouldBreakMaskChain": false,
  "style": {
    "_class": "style",
    "do_objectID": "A169BAD0-B90A-458C-8931-E95DD7B2E431",
    "endDecorationType": 0,
    "miterLimit": 10,
    "startDecorationType": 0
  }
}