{
  "_class": "group",
  "do_objectID": "8630177B-6247-4EFF-AFF8-6479723A8BC6",
  "exportOptions": {
    "_class": "exportOptions",
    "do_objectID": "83E5C4E5-70D2-44D5-8ED4-651352E0F48A",
    "exportFormats": [
    ],
    "includedLayerIds": [
    ],
    "layerOptions": 0,
    "shouldTrim": false
  },
  "frame": {
    "_class": "rect",
    "constrainProportions": true,
    "do_objectID": "E08066DA-E48C-487B-B6E2-C4C27EB7E6E9",
    "height": 45,
    "width": 45,
    "x": 2,
    "y": 56
  },
  "hasClickThrough": false,
  "isFlippedHorizontal": false,
  "isFlippedVertical": false,
  "isLocked": false,
  "isVisible": true,
  "layerListExpandedType": 0,
  "layers": [
    {
      "class": "shapeGroup",
      "id": "31079D35-E8D8-40A9-8022-0DB8868ECB25"
    },
    {
      "class": "group",
      "id": "A4FABFC0-BB31-430F-8318-C9DAA2C5F78A"
    }
  ],
  "name": "logo1",
  "nameIsFixed": true,
  "resizingConstraint": 63,
  "resizingType": 0,
  "rotation": 0,
  "shouldBreakMaskChain": false,
  "style": {
    "_class": "style",
    "do_objectID": "6E4DB8A6-BC8B-4EB5-BCB7-6F98DC60591B",
    "endDecorationType": 0,
    "miterLimit": 10,
    "startDecorationType": 0
  }
}