{
  "_class": "bitmap",
  "clippingMask": "{{0, 0}, {1, 1}}",
  "do_objectID": "AF828D52-B979-403E-B25A-F5F4EE42C2A1",
  "exportOptions": {
    "_class": "exportOptions",
    "do_objectID": "FA622342-AA83-44A8-888D-18059A4F608C",
    "exportFormats": [
    ],
    "includedLayerIds": [
    ],
    "layerOptions": 0,
    "shouldTrim": false
  },
  "fillReplacesImage": false,
  "frame": {
    "_class": "rect",
    "constrainProportions": false,
    "do_objectID": "929E88C1-AD06-4349-8863-2E19FF516842",
    "height": 553,
    "width": 373,
    "x": -2,
    "y": -2
  },
  "image": {
    "_class": "MSJSONFileReference",
    "_ref": "images/0cd400fb53923319b7420ae19dee910307d42563",
    "_ref_class": "MSImageData"
  },
  "isFlippedHorizontal": false,
  "isFlippedVertical": false,
  "isLocked": false,
  "isVisible": true,
  "layerListExpandedType": 0,
  "name": "Image 12625",
  "nameIsFixed": false,
  "resizingConstraint": 63,
  "resizingType": 0,
  "rotation": 0,
  "shouldBreakMaskChain": false,
  "style": {
    "_class": "style",
    "do_objectID": "4E451F12-690E-4DF1-B315-F34890271A39",
    "endDecorationType": 0,
    "miterLimit": 10,
    "startDecorationType": 0
  }
}