{
  "_class": "shapePath",
  "booleanOperation": 0,
  "do_objectID": "E4FEFB99-0A72-4128-9039-6ABCD75643F3",
  "edited": false,
  "exportOptions": {
    "_class": "exportOptions",
    "do_objectID": "FE902CED-BF5B-4F2C-96E5-A1342811BE3C",
    "exportFormats": [
    ],
    "includedLayerIds": [
    ],
    "layerOptions": 0,
    "shouldTrim": false
  },
  "frame": {
    "_class": "rect",
    "constrainProportions": false,
    "do_objectID": "56BA076B-829D-48C8-91D6-5DF21C4E9727",
    "height": 4.6,
    "width": 894.6999999999999,
    "x": 0,
    "y": 0
  },
  "isClosed": true,
  "isFlippedHorizontal": false,
  "isFlippedVertical": false,
  "isLocked": false,
  "isVisible": true,
  "layerListExpandedType": 0,
  "name": "Shape sp-51307-0",
  "nameIsFixed": false,
  "path": {
    "_class": "path",
    "isClosed": true,
    "pointRadiusBehaviour": 0,
    "points": [
      {
        "_class": "curvePoint",
        "cornerRadius": 0,
        "curveFrom": "{0.0025699999999999998, 0.49904700000000002}",
        "curveMode": 1,
        "curveTo": "{0.0025699999999999998, 0.49904700000000002}",
        "hasCurveFrom": false,
        "hasCurveTo": false,
        "point": "{0.0025699999999999998, 0.49904700000000002}"
      },
      {
        "_class": "curvePoint",
        "cornerRadius": 0,
        "curveFrom": "{0.99871399999999999, 0.49904700000000002}",
        "curveMode": 1,
        "curveTo": "{0.99871399999999999, 0.49904700000000002}",
        "hasCurveFrom": false,
        "hasCurveTo": false,
        "point": "{0.99871399999999999, 0.49904700000000002}"
      },
      {
        "_class": "curvePoint",
        "cornerRadius": 0,
        "curveFrom": "{0.99871399999999999, 0.74901600000000002}",
        "curveMode": 1,
        "curveTo": "{0.99871399999999999, 0.74901600000000002}",
        "hasCurveFrom": false,
        "hasCurveTo": false,
        "point": "{0.99871399999999999, 0.74901600000000002}"
      },
      {
        "_class": "curvePoint",
        "cornerRadius": 0,
        "curveFrom": "{0.0025699999999999998, 0.74901600000000002}",
        "curveMode": 1,
        "curveTo": "{0.0025699999999999998, 0.74901600000000002}",
        "hasCurveFrom": false,
        "hasCurveTo": false,
        "point": "{0.0025699999999999998, 0.74901600000000002}"
      }
    ]
  },
  "pointRadiusBehaviour": 0,
  "points": [
    {
      "_class": "curvePoint",
      "cornerRadius": 0,
      "curveFrom": "{0.0025699999999999998, 0.49904700000000002}",
      "curveMode": 1,
      "curveTo": "{0.0025699999999999998, 0.49904700000000002}",
      "hasCurveFrom": false,
      "hasCurveTo": false,
      "point": "{0.0025699999999999998, 0.49904700000000002}"
    },
    {
      "_class": "curvePoint",
      "cornerRadius": 0,
      "curveFrom": "{0.99871399999999999, 0.49904700000000002}",
      "curveMode": 1,
      "curveTo": "{0.99871399999999999, 0.49904700000000002}",
      "hasCurveFrom": false,
      "hasCurveTo": false,
      "point": "{0.99871399999999999, 0.49904700000000002}"
    },
    {
      "_class": "curvePoint",
      "cornerRadius": 0,
      "curveFrom": "{0.99871399999999999, 0.74901600000000002}",
      "curveMode": 1,
      "curveTo": "{0.99871399999999999, 0.74901600000000002}",
      "hasCurveFrom": false,
      "hasCurveTo": false,
      "point": "{0.99871399999999999, 0.74901600000000002}"
    },
    {
      "_class": "curvePoint",
      "cornerRadius": 0,
      "curveFrom": "{0.0025699999999999998, 0.74901600000000002}",
      "curveMode": 1,
      "curveTo": "{0.0025699999999999998, 0.74901600000000002}",
      "hasCurveFrom": false,
      "hasCurveTo": false,
      "point": "{0.0025699999999999998, 0.74901600000000002}"
    }
  ],
  "resizingConstraint": 63,
  "resizingType": 0,
  "rotation": 0,
  "shouldBreakMaskChain": false
}